clitunes/__init__.py
clitunes/main.py
clitunesgithub-0.1.0.dist-info/METADATA
clitunesgithub-0.1.0.dist-info/WHEEL
clitunesgithub-0.1.0.dist-info/entry_points.txt
clitunesgithub-0.1.0.dist-info/top_level.txt
clitunesgithub-0.1.0.dist-info/RECORD
